numbskull/__init__.py
numbskull/__main__.py
numbskull/dataloading.py
numbskull/distributed.py
numbskull/factorgraph.py
numbskull/inference.py
numbskull/learning.py
numbskull/numbskull.py
numbskull/numbskulltypes.py
numbskull/timer.py
numbskull/version.py
numbskull-0.1.1.dist-info/METADATA
numbskull-0.1.1.dist-info/RECORD
numbskull-0.1.1.dist-info/WHEEL
numbskull-0.1.1.dist-info/entry_points.txt
numbskull-0.1.1.dist-info/top_level.txt
