Metadata-Version: 2.1
Name: numbskull
Version: 0.1.1
Summary: sample away
Home-page: UNKNOWN
Author: UNKNOWN
Author-email: UNKNOWN
License: UNKNOWN
Platform: UNKNOWN
Requires-Dist: future
Requires-Dist: futures; python_version == "2.7"
